README.md
pyproject.toml
setup.cfg
setup.py
state_manager/__init__.py
state_manager/storage_settings.py
state_manager/types.py
state_manager.egg-info/PKG-INFO
state_manager.egg-info/SOURCES.txt
state_manager.egg-info/dependency_links.txt
state_manager.egg-info/requires.txt
state_manager.egg-info/top_level.txt
state_manager/dependency/__init__.py
state_manager/dependency/container.py
state_manager/dependency/dependency.py
state_manager/dependency/models.py
state_manager/filters/__init__.py
state_manager/filters/aiogram.py
state_manager/filters/base.py
state_manager/filters/logic.py
state_manager/filters/vkwave.py
state_manager/models/__init__.py
state_manager/models/routers_storage.py
state_manager/models/state.py
state_manager/models/dependencys/__init__.py
state_manager/models/dependencys/aiogram.py
state_manager/models/dependencys/base.py
state_manager/models/dependencys/vkwave.py
state_manager/routes/__init__.py
state_manager/routes/aiogram.py
state_manager/routes/base.py
state_manager/routes/vkwave.py
state_manager/storages/__init__.py
state_manager/storages/base.py
state_manager/storages/memory.py
state_manager/storages/redis.py
state_manager/storages/state_storage.py
state_manager/utils/__init__.py
state_manager/utils/check.py
state_manager/utils/search.py
state_manager/utils/utils.py
tests/__init__.py
tests/filters/__init__.py
tests/filters/test_logic.py
tests/models/__init__.py
tests/storages/__init__.py
tests/storages/test_storages.py
tests/utils/__init__.py
tests/utils/test_check.py
tests/utils/test_dependencies.py
tests/utils/test_utils.py