Metadata-Version: 2.1
Name: state-manager
Version: 0.2.0
Summary: fsm for people
Home-page: https://github.com/Bloodielie/state_manager
Author: Bloodie_lie
Author-email: riopro2812@gmail.com
License: Apache-2.0 License
Platform: UNKNOWN
Classifier: Programming Language :: Python :: 3.8
Classifier: Topic :: Internet
Requires-Python: >=3.8
Provides-Extra: full
Provides-Extra: vk
Provides-Extra: telegram
